{"singlePage": [], "startSite": "", "filingNum": "", "onePageListNum": 15, "commentLabelColor": "#006b75", "yearColorList": ["#bc4c00", "#0969da", "#1f883d", "#A333D0"], "i18n": "EN", "themeMode": "manual", "dayTheme": "light", "nightTheme": "dark_colorblind", "urlMode": "pinyin", "script": "", "style": "", "head": "", "indexScript": "", "indexStyle": "", "bottomText": "", "showPostSource": 1, "iconList": {}, "UTC": 8, "rssSplit": "sentence", "exlink": {}, "needComment": 1, "allHead": "", "title": "KilmuDMA", "displayTitle": "KilmuDMA", "subTitle": "Top-Tier DMA Firmware", "avatarUrl": "https://avatars.githubusercontent.com/u/155318836?v=4", "homeUrl": "https://blog.kilmu.com", "GMEEK_VERSION": "last", "postListJson": {"P1": {"htmlDir": "docs/post/DMA CFW Guide.html", "labels": ["Documentation"], "postTitle": "DMA CFW Guide", "postUrl": "post/DMA%20CFW%20Guide.html", "postSourceUrl": "https://github.com/kilmu1337/Kilmu-Blog/issues/1", "commentNum": 0, "wordCount": 10, "description": "to be done.", "top": 1, "createdAt": 1741782481, "style": "", "script": "", "head": "", "ogImage": "https://avatars.githubusercontent.com/u/155318836?v=4", "createdDate": "2025-03-12", "dateLabelColor": "#0969da"}, "P2": {"htmlDir": "docs/post/DMA Trouble Shooting.html", "labels": ["Documentation"], "postTitle": "DMA Trouble Shooting", "postUrl": "post/DMA%20Trouble%20Shooting.html", "postSourceUrl": "https://github.com/kilmu1337/Kilmu-Blog/issues/2", "commentNum": 0, "wordCount": 1676, "description": "# General Inspection Process\n1.", "top": 0, "createdAt": 1741856076, "style": "", "script": "", "head": "", "ogImage": "https://avatars.githubusercontent.com/u/155318836?v=4", "createdDate": "2025-03-13", "dateLabelColor": "#0969da"}, "P3": {"htmlDir": "docs/post/How to Flash DMA Firmware.html", "labels": ["Documentation"], "postTitle": "How to Flash DMA Firmware", "postUrl": "post/How%20to%20Flash%20DMA%20Firmware.html", "postSourceUrl": "https://github.com/kilmu1337/Kilmu-Blog/issues/3", "commentNum": 0, "wordCount": 4416, "description": "# Flash Tool Link\n [https://github.", "top": 0, "createdAt": 1742115920, "style": "", "script": "", "head": "", "ogImage": "https://avatars.githubusercontent.com/u/155318836?v=4", "createdDate": "2025-03-16", "dateLabelColor": "#0969da"}, "P4": {"htmlDir": "docs/post/DMA-tong-yong-shao-lu-jiao-cheng.html", "labels": ["Documentation"], "postTitle": "DMA\u901a\u7528\u70e7\u5f55\u6559\u7a0b", "postUrl": "post/DMA-tong-yong-shao-lu-jiao-cheng.html", "postSourceUrl": "https://github.com/kilmu1337/Kilmu-Blog/issues/4", "commentNum": 0, "wordCount": 2280, "description": "# \u9879\u76ee\u5730\u5740\n [https://github.", "top": 0, "createdAt": 1742116288, "style": "", "script": "", "head": "", "ogImage": "https://avatars.githubusercontent.com/u/155318836?v=4", "createdDate": "2025-03-16", "dateLabelColor": "#0969da"}, "P5": {"htmlDir": "docs/post/How to Get the DNA ID of DMA Card.html", "labels": ["Documentation"], "postTitle": "How to Get the DNA ID of DMA Card", "postUrl": "post/How%20to%20Get%20the%20DNA%20ID%20of%20DMA%20Card.html", "postSourceUrl": "https://github.com/kilmu1337/Kilmu-Blog/issues/5", "commentNum": 0, "wordCount": 3076, "description": "# Tool Link\n [https://github.", "top": 0, "createdAt": 1742117654, "style": "", "script": "", "head": "", "ogImage": "https://avatars.githubusercontent.com/u/155318836?v=4", "createdDate": "2025-03-16", "dateLabelColor": "#0969da"}, "P6": {"htmlDir": "docs/post/DMA-huo-qu-DNA ID-jiao-cheng.html", "labels": ["Documentation"], "postTitle": "DMA\u83b7\u53d6DNA ID\u6559\u7a0b", "postUrl": "post/DMA-huo-qu-DNA%20ID-jiao-cheng.html", "postSourceUrl": "https://github.com/kilmu1337/Kilmu-Blog/issues/6", "commentNum": 0, "wordCount": 1784, "description": "# \u9879\u76ee\u5730\u5740\n [https://github.", "top": 0, "createdAt": 1742117922, "style": "", "script": "", "head": "", "ogImage": "https://avatars.githubusercontent.com/u/155318836?v=4", "createdDate": "2025-03-16", "dateLabelColor": "#0969da"}, "P7": {"htmlDir": "docs/post/Some Basic Knowledge about DMA.html", "labels": ["Documentation"], "postTitle": "Some Basic Knowledge about DMA", "postUrl": "post/Some%20Basic%20Knowledge%20about%20DMA.html", "postSourceUrl": "https://github.com/kilmu1337/Kilmu-Blog/issues/7", "commentNum": 0, "wordCount": 2594, "description": "### What is `Pcileech`?\n\nCurrently, all DMA firmware is based on [pcileech-fpga](https://github.", "top": 1, "createdAt": 1742130843, "style": "", "script": "", "head": "", "ogImage": "https://avatars.githubusercontent.com/u/155318836?v=4", "createdDate": "2025-03-16", "dateLabelColor": "#0969da"}}, "singeListJson": {}, "labelColorDict": {"bug": "#d73a4a", "Documentation": "#0075ca", "duplicate": "#cfd3d7", "enhancement": "#a2eeef", "good first issue": "#7057ff", "help wanted": "#008672", "invalid": "#e4e669", "question": "#d876e3", "wontfix": "#ffffff"}, "faviconUrl": "https://avatars.githubusercontent.com/u/155318836?v=4", "ogImage": "https://avatars.githubusercontent.com/u/155318836?v=4", "primerCSS": "<link href='https://mirrors.sustech.edu.cn/cdnjs/ajax/libs/Primer/21.0.7/primer.css' rel='stylesheet' />", "prevUrl": "disabled", "nextUrl": "disabled"}